get_ipos-0.0.1.dist-info/METADATA
get_ipos-0.0.1.dist-info/RECORD
get_ipos-0.0.1.dist-info/WHEEL
get_ipos-0.0.1.dist-info/top_level.txt
ipos/__init__.py
ipos/get_ipos.py
ipos_list/__init__.py
ipos_list/bse.py
ipos_list/euronext.py
ipos_list/lse.py
ipos_list/nasdaq.py
ipos_list/nsei.py
ipos_list/nyse.py
ipos_list/sehk.py
ipos_list/tsx.py
ipos_list/tyo.py
